COPYING
COPYING.lesser
MANIFEST.in
NOTICE
README.md
requirements.txt
setup.py
Newgram.egg-info/PKG-INFO
Newgram.egg-info/SOURCES.txt
Newgram.egg-info/dependency_links.txt
Newgram.egg-info/not-zip-safe
Newgram.egg-info/requires.txt
Newgram.egg-info/top_level.txt
compiler/__init__.py
compiler/api/__init__.py
compiler/api/compiler.py
compiler/api/source/auth_key.tl
compiler/api/source/main_api.tl
compiler/api/source/sys_msgs.tl
compiler/api/template/combinator.txt
compiler/api/template/type.txt
compiler/docs/__init__.py
compiler/docs/compiler.py
compiler/docs/template/page.txt
compiler/docs/template/toctree.txt
compiler/errors/__init__.py
compiler/errors/compiler.py
compiler/errors/sort.py
compiler/errors/source/303_SEE_OTHER.tsv
compiler/errors/source/400_BAD_REQUEST.tsv
compiler/errors/source/401_UNAUTHORIZED.tsv
compiler/errors/source/403_FORBIDDEN.tsv
compiler/errors/source/406_NOT_ACCEPTABLE.tsv
compiler/errors/source/420_FLOOD.tsv
compiler/errors/source/500_INTERNAL_SERVER_ERROR.tsv
compiler/errors/source/503_SERVICE_UNAVAILABLE.tsv
compiler/errors/template/class.txt
compiler/errors/template/sub_class.txt
newgram/__init__.py
newgram/client.py
newgram/dispatcher.py
newgram/emoji.py
newgram/file_id.py
newgram/filters.py
newgram/mime_types.py
newgram/py.typed
newgram/sync.py
newgram/utils.py
newgram/connection/__init__.py
newgram/connection/connection.py
newgram/connection/transport/__init__.py
newgram/connection/transport/tcp/__init__.py
newgram/connection/transport/tcp/tcp.py
newgram/connection/transport/tcp/tcp_abridged.py
newgram/connection/transport/tcp/tcp_abridged_o.py
newgram/connection/transport/tcp/tcp_full.py
newgram/connection/transport/tcp/tcp_intermediate.py
newgram/connection/transport/tcp/tcp_intermediate_o.py
newgram/crypto/__init__.py
newgram/crypto/aes.py
newgram/crypto/mtproto.py
newgram/crypto/prime.py
newgram/crypto/rsa.py
newgram/enums/__init__.py
newgram/enums/auto_name.py
newgram/enums/chat_action.py
newgram/enums/chat_event_action.py
newgram/enums/chat_member_status.py
newgram/enums/chat_members_filter.py
newgram/enums/chat_type.py
newgram/enums/message_entity_type.py
newgram/enums/message_media_type.py
