Metadata-Version: 2.1
Name: Newgram
Version: 0.0.5
Summary: Elegant, modern and asynchronous Telegram MTProto API framework in Python for users and bots
Home-page: https://github.com/jokokendi
Author: Noel
Author-email: noel@newgram.org
License: LGPLv3
Download-URL: https://github.com/jokokendi/newgram/releases/latest
Project-URL: Tracker, https://github.com/jokokendi/newgram/issues
Project-URL: Community, https://t.me/newgram
Project-URL: Source, https://github.com/jokokendi/newgram
Project-URL: Documentation, https://docs.newgram.org
Keywords: telegram chat messenger mtproto api client library python
Platform: UNKNOWN
Classifier: Programming Language :: Python :: 3
Classifier: Programming Language :: Python :: 3.8
Classifier: Programming Language :: Python :: 3.9
Classifier: Programming Language :: Python :: 3.10
Classifier: License :: OSI Approved :: GNU General Public License v3 (GPLv3)
Classifier: Operating System :: OS Independent
Requires-Python: ~=3.7
License-File: COPYING
License-File: COPYING.lesser
License-File: NOTICE
